plone.app.multilingualindexes-3.0.2-py3.9-nspkg.pth
plone/app/multilingualindexes/__init__.py
plone/app/multilingualindexes/browser.py
plone/app/multilingualindexes/configure.zcml
plone/app/multilingualindexes/controlpanel.py
plone/app/multilingualindexes/interfaces.py
plone/app/multilingualindexes/languagefallback.py
plone/app/multilingualindexes/patches.py
plone/app/multilingualindexes/querymodifiers.py
plone/app/multilingualindexes/setuphandlers.py
plone/app/multilingualindexes/testing.py
plone/app/multilingualindexes/tgpath.py
plone/app/multilingualindexes/utils.py
plone/app/multilingualindexes/locales/plone.app.multilingualindexes.pot
plone/app/multilingualindexes/locales/update.sh
plone/app/multilingualindexes/profiles/default/browserlayer.xml
plone/app/multilingualindexes/profiles/default/catalog.xml
plone/app/multilingualindexes/profiles/default/controlpanel.xml
plone/app/multilingualindexes/profiles/default/metadata.xml
plone/app/multilingualindexes/profiles/default/registry.xml
plone/app/multilingualindexes/profiles/uninstall/browserlayer.xml
plone/app/multilingualindexes/tests/__init__.py
plone/app/multilingualindexes/tests/test_languagefallback.py
plone/app/multilingualindexes/tests/test_setup.py
plone/app/multilingualindexes/tests/test_tgpath.py
plone/app/multilingualindexes/tests/test_utils.py
plone/app/multilingualindexes/www/addLFBIndex.dtml
plone/app/multilingualindexes/www/browseIndex.dtml
plone/app/multilingualindexes/www/index.gif
plone/app/multilingualindexes/www/manageLFBIndex.dtml
plone.app.multilingualindexes-3.0.2.dist-info/METADATA
plone.app.multilingualindexes-3.0.2.dist-info/WHEEL
plone.app.multilingualindexes-3.0.2.dist-info/entry_points.txt
plone.app.multilingualindexes-3.0.2.dist-info/namespace_packages.txt
plone.app.multilingualindexes-3.0.2.dist-info/top_level.txt
plone.app.multilingualindexes-3.0.2.dist-info/RECORD
