Metadata-Version: 2.1
Name: plone.app.multilingualindexes
Version: 3.0.2
Summary: Multilingual Catalog Indexes for Plone
Home-page: https://github.com/plone/plone.app.multilingualindexes
Author: Jens W. Klein
Author-email: jk@kleinundpartner.at
License: GPL version 2
Keywords: Python,Plone,multilingual,translation
Platform: UNKNOWN
Classifier: Development Status :: 5 - Production/Stable
Classifier: Environment :: Web Environment
Classifier: Framework :: Plone
Classifier: Framework :: Plone :: Addon
Classifier: Framework :: Plone :: 5.2
Classifier: Framework :: Plone :: 6.0
Classifier: Programming Language :: Python
Classifier: Programming Language :: Python :: 3.7
Classifier: Programming Language :: Python :: 3.8
Classifier: Programming Language :: Python :: 3.9
Classifier: Operating System :: OS Independent
Classifier: License :: OSI Approved :: GNU General Public License v2 (GPLv2)
Requires-Dist: setuptools
Requires-Dist: Products.CMFPlone (>=5.2.1)
Requires-Dist: plone.app.querystring (>=1.4.14)
Requires-Dist: plone.app.theming (>=4.1.3)
Provides-Extra: test
Requires-Dist: plone.app.testing ; extra == 'test'
Requires-Dist: plone.app.multilingual[test] ; extra == 'test'
